setup.py
drf_any_permissions.egg-info/PKG-INFO
drf_any_permissions.egg-info/SOURCES.txt
drf_any_permissions.egg-info/dependency_links.txt
drf_any_permissions.egg-info/requires.txt
drf_any_permissions.egg-info/top_level.txt
rest_any_permissions/__init__.py
rest_any_permissions/permissions.py