Metadata-Version: 1.0
Name: drf-any-permissions
Version: 0.0.1
Summary: Permissions don't have to be all or nothing anymore, make integrating different authentication types easier.
Home-page: https://github.com/kevin-brown/drf-any-permissions/
Author: Kevin Brown
Author-email: kbrown@rediker.com
License: MIT
Platform: UNKNOWN
